scicast/R_qgraph.py
scicast/__init__.py
scicast/cluster.py
scicast/correlation.py
scicast/dim_reduction.py
scicast/heatmaps.py
scicast/matrix_filter.py
scicast/normalize_counts.py
scicast/sci_load.py
scicast/scicast_argparse.py
scicast/significance_testing.py
scicast/stability_test.py
scicast/tkinter_scicast.py
scicast-0.8.27.dist-info/DESCRIPTION.rst
scicast-0.8.27.dist-info/METADATA
scicast-0.8.27.dist-info/RECORD
scicast-0.8.27.dist-info/WHEEL
scicast-0.8.27.dist-info/entry_points.txt
scicast-0.8.27.dist-info/metadata.json
scicast-0.8.27.dist-info/top_level.txt
