Metadata-Version: 2.0
Name: scicast
Version: 0.8.27
Summary: scicast: Single Cell Iterative Clustering and Statistical Testing. A package for interrogating single cell sequencing data.
Home-page: https://github.com/iandriver/scicast
Author: Ian Driver
Author-email: ian.driver@ucsf.edu
License: MIT
Download-URL: https://github.com/iandriver/scicast
Keywords: single-cell single cell RNA-seq sequencing clustering PCA k-means
Platform: UNKNOWN
Classifier: Intended Audience :: Science/Research
Classifier: Programming Language :: Python :: 2.7
Classifier: Programming Language :: Python :: 3.5
Classifier: Programming Language :: Python :: 3.6
Classifier: License :: OSI Approved :: MIT License
Classifier: Topic :: Scientific/Engineering :: Visualization
Classifier: Topic :: Scientific/Engineering :: Bio-Informatics
Classifier: Operating System :: POSIX
Classifier: Operating System :: Unix
Classifier: Operating System :: MacOS
